free_range_rust-0.1.9.dist-info/METADATA
free_range_rust-0.1.9.dist-info/WHEEL
free_range_rust-0.1.9.dist-info/licenses/LICENSE
free_range_rust/__init__.py
free_range_rust/free_range_rust.cpython-39-x86_64-linux-gnu.so
free_range_rust-0.1.9.dist-info/RECORD
