Metadata-Version: 2.4
Name: free_range_rust
Version: 0.1.9
License-File: LICENSE
Summary: Python bindings in Rust for singificantly faster computation for the free-range-zoo library
Author: C4 Patino <c4patino@gmail.com>
Author-email: C4 Patino <c4patino@gmail.com>
Project-URL: Source Code, https://github.com/C4theBomb/free-range-rust
